onnx_array_api/__init__.py
onnx_array_api/__main__.py
onnx_array_api/_command_lines_parser.py
onnx_array_api/_helpers.py
onnx_array_api/annotations.py
onnx_array_api/cache.py
onnx_array_api/ext_test_case.py
onnx_array_api/profiling.py
onnx_array_api/array_api/__init__.py
onnx_array_api/array_api/_onnx_common.py
onnx_array_api/array_api/onnx_numpy.py
onnx_array_api/array_api/onnx_ort.py
onnx_array_api/graph_api/__init__.py
onnx_array_api/graph_api/graph_builder.py
onnx_array_api/light_api/__init__.py
onnx_array_api/light_api/_op_var.py
onnx_array_api/light_api/_op_vars.py
onnx_array_api/light_api/model.py
onnx_array_api/light_api/var.py
onnx_array_api/npx/__init__.py
onnx_array_api/npx/npx_array_api.py
onnx_array_api/npx/npx_constants.py
onnx_array_api/npx/npx_core_api.py
onnx_array_api/npx/npx_function_implementation.py
onnx_array_api/npx/npx_functions.py
onnx_array_api/npx/npx_functions_test.py
onnx_array_api/npx/npx_graph_builder.py
onnx_array_api/npx/npx_helper.py
onnx_array_api/npx/npx_jit_eager.py
onnx_array_api/npx/npx_numpy_tensors.py
onnx_array_api/npx/npx_tensors.py
onnx_array_api/npx/npx_types.py
onnx_array_api/npx/npx_var.py
onnx_array_api/ort/__init__.py
onnx_array_api/ort/ort_optimizers.py
onnx_array_api/ort/ort_profile.py
onnx_array_api/ort/ort_tensors.py
onnx_array_api/plotting/__init__.py
onnx_array_api/plotting/_helper.py
onnx_array_api/plotting/dot_plot.py
onnx_array_api/plotting/graphviz_helper.py
onnx_array_api/plotting/stat_plot.py
onnx_array_api/plotting/text_plot.py
onnx_array_api/reference/__init__.py
onnx_array_api/reference/evaluator.py
onnx_array_api/reference/evaluator_yield.py
onnx_array_api/reference/ops/__init__.py
onnx_array_api/reference/ops/op_cast_like.py
onnx_array_api/reference/ops/op_concat.py
onnx_array_api/reference/ops/op_constant_of_shape.py
onnx_array_api/reference/ops/op_fused_matmul.py
onnx_array_api/reference/ops/op_memcpy_host.py
onnx_array_api/reference/ops/op_quick_gelu.py
onnx_array_api-0.3.1.dist-info/licenses/LICENSE.txt
onnx_array_api-0.3.1.dist-info/METADATA
onnx_array_api-0.3.1.dist-info/WHEEL
onnx_array_api-0.3.1.dist-info/top_level.txt
onnx_array_api-0.3.1.dist-info/RECORD
